{
  "_national": {
    "turnoutChange": 0.15,
    "incumbencyFatigue": -0.08,
    "turncoatPenalty": -0.12,
    "recontestBonus": 0.04,
    "sameConstituencyBonus": 0.03,
    "previousMarginFactor": -0.06,
    "enopFactor": -0.04,
    "nCandFactor": -0.02,
    "constituencyTypeFactor": 0.01,
    "genderFactor": -0.02,
    "partyStrengthFactor": 0.1,
    "partyVoteShareFactor": 0.08
  },
  "Tamil_Nadu": {
    "turnoutChange": 0.18,
    "incumbencyFatigue": -0.1,
    "turncoatPenalty": -0.15,
    "recontestBonus": 0.05,
    "sameConstituencyBonus": 0.03,
    "previousMarginFactor": -0.07,
    "enopFactor": -0.05,
    "nCandFactor": -0.03,
    "constituencyTypeFactor": 0.02,
    "genderFactor": -0.01,
    "partyStrengthFactor": 0.12,
    "partyVoteShareFactor": 0.09
  },
  "Maharashtra": {
    "turnoutChange": 0.14,
    "incumbencyFatigue": -0.09,
    "turncoatPenalty": -0.11,
    "recontestBonus": 0.04,
    "sameConstituencyBonus": 0.03,
    "previousMarginFactor": -0.05,
    "enopFactor": -0.04,
    "nCandFactor": -0.02,
    "constituencyTypeFactor": 0.01,
    "genderFactor": -0.02,
    "partyStrengthFactor": 0.09,
    "partyVoteShareFactor": 0.07
  },
  "Uttar_Pradesh": {
    "turnoutChange": 0.16,
    "incumbencyFatigue": -0.07,
    "turncoatPenalty": -0.1,
    "recontestBonus": 0.03,
    "sameConstituencyBonus": 0.02,
    "previousMarginFactor": -0.06,
    "enopFactor": -0.05,
    "nCandFactor": -0.03,
    "constituencyTypeFactor": 0.02,
    "genderFactor": -0.03,
    "partyStrengthFactor": 0.11,
    "partyVoteShareFactor": 0.08
  },
  "West_Bengal": {
    "turnoutChange": 0.17,
    "incumbencyFatigue": -0.09,
    "turncoatPenalty": -0.13,
    "recontestBonus": 0.05,
    "sameConstituencyBonus": 0.04,
    "previousMarginFactor": -0.07,
    "enopFactor": -0.03,
    "nCandFactor": -0.02,
    "constituencyTypeFactor": 0.01,
    "genderFactor": -0.01,
    "partyStrengthFactor": 0.1,
    "partyVoteShareFactor": 0.09
  },
  "Karnataka": {
    "turnoutChange": 0.15,
    "incumbencyFatigue": -0.08,
    "turncoatPenalty": -0.11,
    "recontestBonus": 0.04,
    "sameConstituencyBonus": 0.03,
    "previousMarginFactor": -0.06,
    "enopFactor": -0.04,
    "nCandFactor": -0.02,
    "constituencyTypeFactor": 0.01,
    "genderFactor": -0.02,
    "partyStrengthFactor": 0.1,
    "partyVoteShareFactor": 0.08
  },
  "Bihar": {
    "turnoutChange": 0.14,
    "incumbencyFatigue": -0.07,
    "turncoatPenalty": -0.1,
    "recontestBonus": 0.03,
    "sameConstituencyBonus": 0.02,
    "previousMarginFactor": -0.05,
    "enopFactor": -0.05,
    "nCandFactor": -0.03,
    "constituencyTypeFactor": 0.02,
    "genderFactor": -0.03,
    "partyStrengthFactor": 0.09,
    "partyVoteShareFactor": 0.07
  },
  "Rajasthan": {
    "turnoutChange": 0.16,
    "incumbencyFatigue": -0.1,
    "turncoatPenalty": -0.12,
    "recontestBonus": 0.04,
    "sameConstituencyBonus": 0.03,
    "previousMarginFactor": -0.06,
    "enopFactor": -0.04,
    "nCandFactor": -0.02,
    "constituencyTypeFactor": 0.01,
    "genderFactor": -0.02,
    "partyStrengthFactor": 0.1,
    "partyVoteShareFactor": 0.08
  },
  "Madhya_Pradesh": {
    "turnoutChange": 0.15,
    "incumbencyFatigue": -0.09,
    "turncoatPenalty": -0.11,
    "recontestBonus": 0.04,
    "sameConstituencyBonus": 0.03,
    "previousMarginFactor": -0.06,
    "enopFactor": -0.04,
    "nCandFactor": -0.02,
    "constituencyTypeFactor": 0.01,
    "genderFactor": -0.02,
    "partyStrengthFactor": 0.1,
    "partyVoteShareFactor": 0.08
  },
  "Andhra_Pradesh": {
    "turnoutChange": 0.15,
    "incumbencyFatigue": -0.08,
    "turncoatPenalty": -0.1,
    "recontestBonus": 0.04,
    "sameConstituencyBonus": 0.03,
    "previousMarginFactor": -0.05,
    "enopFactor": -0.03,
    "nCandFactor": -0.02,
    "constituencyTypeFactor": 0.01,
    "genderFactor": -0.02,
    "partyStrengthFactor": 0.09,
    "partyVoteShareFactor": 0.07
  },
  "Gujarat": {
    "turnoutChange": 0.14,
    "incumbencyFatigue": -0.07,
    "turncoatPenalty": -0.1,
    "recontestBonus": 0.03,
    "sameConstituencyBonus": 0.02,
    "previousMarginFactor": -0.05,
    "enopFactor": -0.03,
    "nCandFactor": -0.02,
    "constituencyTypeFactor": 0.01,
    "genderFactor": -0.02,
    "partyStrengthFactor": 0.11,
    "partyVoteShareFactor": 0.08
  }
}
